mite_cli/__main__.py
mite_cli/envbuild_withreqs.py
mite_cli/new_project.py
mite_cli-0.2.2.dist-info/METADATA
mite_cli-0.2.2.dist-info/WHEEL
mite_cli-0.2.2.dist-info/entry_points.txt
mite_cli-0.2.2.dist-info/top_level.txt
mite_cli-0.2.2.dist-info/RECORD
