Metadata-Version: 2.1
Name: mite-cli
Version: 0.2.2
Summary: mite cli tool
Home-page: https://github.com/ryanlinnit-sky/mite-cli/
License: UNKNOWN
Platform: UNKNOWN
Classifier: License :: OSI Approved :: MIT License
Classifier: Programming Language :: Python
Classifier: Programming Language :: Python :: 3
Classifier: Programming Language :: Python :: 3.8
Classifier: Programming Language :: Python :: 3.9
Classifier: Operating System :: POSIX :: Linux
Requires-Dist: docopt
Requires-Dist: GitPython
Requires-Dist: yaspin
